django_infoNavigator-0.18.dist-info/DESCRIPTION.rst
django_infoNavigator-0.18.dist-info/METADATA
django_infoNavigator-0.18.dist-info/RECORD
django_infoNavigator-0.18.dist-info/WHEEL
django_infoNavigator-0.18.dist-info/metadata.json
django_infoNavigator-0.18.dist-info/top_level.txt
infoNavigator/__init__.py
infoNavigator/views.py
infoNavigator/templates/infoNavigator/choose_columns_template.html
infoNavigator/templates/infoNavigator/default_record_template.html
infoNavigator/templates/infoNavigator/default_records_template.html
infoNavigator/templates/infoNavigator/template_wrapper.html
